ppo/__init__.py
ppo/category.py
ppo/db.py
ppo/detail.py
ppo/find.py
ppo/make.py
ppo/modify.py
ppo/page.py
ppo/plan.py
ppo/potato.py
ppo/remove.py
ppo/version.py
testpotato-2.5.6.dist-info/METADATA
testpotato-2.5.6.dist-info/RECORD
testpotato-2.5.6.dist-info/WHEEL
testpotato-2.5.6.dist-info/entry_points.txt
testpotato-2.5.6.dist-info/top_level.txt
