Metadata-Version: 2.1
Name: testpotato
Version: 2.5.6
Summary: This is very usual todo-list
Home-page: UNKNOWN
Author: Team_potato
Author-email: UNKNOWN
License: UNKNOWN
Platform: UNKNOWN
Classifier: Programming Language :: Python :: 3.6
